README.md
setup.py
lrn_rate_limitter_app.egg-info/PKG-INFO
lrn_rate_limitter_app.egg-info/SOURCES.txt
lrn_rate_limitter_app.egg-info/dependency_links.txt
lrn_rate_limitter_app.egg-info/requires.txt
lrn_rate_limitter_app.egg-info/top_level.txt
rate_limitter/__init__.py
rate_limitter/limitter.py