Metadata-Version: 2.1
Name: lrn-rate-limitter-app
Version: 0.1.0
Summary: A Python package for rate limitter
Home-page: https://github.com/raviforcebolt/rate_limitter.git
Author: Mohd Ravi
Author-email: mohd.ravi@cloudanalogy.com
License: UNKNOWN
Platform: UNKNOWN
Classifier: Programming Language :: Python :: 3
Classifier: License :: OSI Approved :: MIT License
Classifier: Operating System :: OS Independent
Requires-Python: >=3.8
